osmg/__init__.py
osmg/get_latest_pypi_version.py
osmg/py.typed
osmg/analysis/__init__.py
osmg/analysis/common.py
osmg/analysis/ground_motion_utils.py
osmg/analysis/load_case.py
osmg/analysis/recorders.py
osmg/analysis/solver.py
osmg/analysis/supports.py
osmg/core/__init__.py
osmg/core/common.py
osmg/core/gridsystem.py
osmg/core/model.py
osmg/core/osmg_collections.py
osmg/core/uid_object.py
osmg/creators/__init__.py
osmg/creators/component.py
osmg/creators/material.py
osmg/creators/section.py
osmg/creators/uid.py
osmg/creators/zerolength.py
osmg/data/sections.json
osmg/geometry/__init__.py
osmg/geometry/line.py
osmg/geometry/mesh.py
osmg/geometry/mesh_shapes.py
osmg/geometry/transformations.py
osmg/graphics/__init__.py
osmg/graphics/objects.py
osmg/graphics/plotly.py
osmg/graphics/visibility.py
osmg/model_objects/__init__.py
osmg/model_objects/element.py
osmg/model_objects/friction_model.py
osmg/model_objects/node.py
osmg/model_objects/section.py
osmg/model_objects/uniaxial_material.py
osmg/postprocessing/__init__.py
osmg/preprocessing/__init__.py
osmg/tests/__init__.py
osmg/tests/test_line.py
osmg/tests/test_mesh.py
osmg/tests/test_transformations.py
osmg/tests/analysis/__init__.py
osmg/tests/analysis/test_load_case.py
osmg/tests/analysis/test_supports.py
osmg/tests/core/__init__.py
osmg/tests/core/test_common.py
osmg/tests/core/test_gridsystem.py
osmg/tests/core/test_uid_object.py
osmg/tests/creators/__init__.py
osmg/tests/creators/test_uid.py
osmg/tests/elements/__init__.py
osmg/tests/elements/test_node.py
osmg/tests/verification/__init__.py
osmg/tests/verification/braced_frame.py
osmg/tests/verification/test_offset_and_basic_forces.py
osmg/tests/verification/opensees_only/__init__.py
osmg/tests/verification/opensees_only/openseespy_truss.py
osmg/tests/verification/opensees_only/opsvis_frame.py
osmg-1.0.13.dist-info/licenses/LICENSE
osmg-1.0.13.dist-info/METADATA
osmg-1.0.13.dist-info/WHEEL
osmg-1.0.13.dist-info/top_level.txt
osmg-1.0.13.dist-info/RECORD
